LICENSE
MANIFEST.in
README.rst
setup.py
octarine_plumbum.egg-info/PKG-INFO
octarine_plumbum.egg-info/SOURCES.txt
octarine_plumbum.egg-info/dependency_links.txt
octarine_plumbum.egg-info/top_level.txt
plumbum/__init__.py
plumbum/_testtools.py
plumbum/colors.py
plumbum/lib.py
plumbum/version.py
plumbum/cli/__init__.py
plumbum/cli/application.py
plumbum/cli/config.py
plumbum/cli/i18n.py
plumbum/cli/image.py
plumbum/cli/progress.py
plumbum/cli/switches.py
plumbum/cli/terminal.py
plumbum/cli/termsize.py
plumbum/cli/i18n/de/LC_MESSAGES/plumbum.cli.mo
plumbum/cli/i18n/fr/LC_MESSAGES/plumbum.cli.mo
plumbum/cli/i18n/nl/LC_MESSAGES/plumbum.cli.mo
plumbum/cli/i18n/ru/LC_MESSAGES/plumbum.cli.mo
plumbum/colorlib/__init__.py
plumbum/colorlib/__main__.py
plumbum/colorlib/_ipython_ext.py
plumbum/colorlib/factories.py
plumbum/colorlib/names.py
plumbum/colorlib/styles.py
plumbum/commands/__init__.py
plumbum/commands/base.py
plumbum/commands/daemons.py
plumbum/commands/modifiers.py
plumbum/commands/processes.py
plumbum/fs/__init__.py
plumbum/fs/atomic.py
plumbum/fs/mounts.py
plumbum/machines/__init__.py
plumbum/machines/_windows.py
plumbum/machines/base.py
plumbum/machines/env.py
plumbum/machines/local.py
plumbum/machines/paramiko_machine.py
plumbum/machines/remote.py
plumbum/machines/session.py
plumbum/machines/ssh_machine.py
plumbum/path/__init__.py
plumbum/path/base.py
plumbum/path/local.py
plumbum/path/remote.py
plumbum/path/utils.py