Metadata-Version: 1.1
Name: octarine-plumbum
Version: 0.0.2
Summary: Plumbum: shell combinators library
Home-page: https://plumbum.readthedocs.io
Author: Tomer Filiba
Author-email: tomerfiliba@gmail.com
License: MIT
Keywords: path,local,remote,ssh,shell,pipe,popen,process,execution,color,cli
Platform: POSIX
Platform: Windows
Classifier: Development Status :: 5 - Production/Stable
Classifier: License :: OSI Approved :: MIT License
Classifier: Operating System :: Microsoft :: Windows
Classifier: Operating System :: POSIX
Classifier: Programming Language :: Python :: 2.6
Classifier: Programming Language :: Python :: 2.7
Classifier: Programming Language :: Python :: 3
Classifier: Programming Language :: Python :: 3.4
Classifier: Programming Language :: Python :: 3.5
Classifier: Programming Language :: Python :: 3.6
Classifier: Topic :: Software Development :: Build Tools
Classifier: Topic :: System :: Systems Administration
Provides: plumbum
